lammy/__init__.py
lammy/api.py
lammy/cli.py
lammy/config.py
lammy/models.py
lammy/render.py
lammy/ssh.py
lammy-0.1.7.dist-info/WHEEL
lammy-0.1.7.dist-info/entry_points.txt
lammy-0.1.7.dist-info/METADATA
lammy-0.1.7.dist-info/RECORD
