Metadata-Version: 2.3
Name: lammy
Version: 0.1.7
Summary: lambda api cli tool
Author: k
Author-email: k <keatone@gmail.com>
Requires-Dist: click>=8.3.0
Requires-Dist: httpx>=0.28.1
Requires-Dist: rich>=14.2.0
Requires-Python: >=3.12
